guess_number_bo
