Metadata-Version: 1.0
Name: guess-number-bo
Version: 0.0.2
Summary: Guess a number game
Home-page: UNKNOWN
Author: Bo Ma
Author-email: UNKNOWN
License: UNKNOWN
Platform: UNKNOWN
